Metadata-Version: 1.1
Name: python3-vote-core
Version: 20170329.0
Summary: An implementation of various election methods, most notably the Schulze Method and Schulze STV. -- Python 3 Only
Home-page: https://github.com/bradbeattie/python-vote-core
Author: Brad Beattie
Author-email: bradbeattie@gmail com
License: GPLv3
Keywords: library election
Platform: UNKNOWN
Classifier: Development Status :: 5 - Production/Stable
Classifier: License :: OSI Approved :: GNU General Public License (GPL)
Classifier: Programming Language :: Python
Classifier: Programming Language :: Python :: 3 :: Only
Classifier: Topic :: Scientific/Engineering :: Mathematics
